schema_first/__init__.py
schema_first/exceptions.py
schema_first/loaders/__init__.py
schema_first/loaders/exc.py
schema_first/loaders/yaml_loader.py
schema_first/openapi/__init__.py
schema_first/openapi/exc.py
schema_first/openapi/schemas/__init__.py
schema_first/openapi/schemas/base.py
schema_first/openapi/schemas/constants.py
schema_first/openapi/schemas/fields.py
schema_first/openapi/schemas/v3_1_1/components_object_schema.py
schema_first/openapi/schemas/v3_1_1/contact_schema.py
schema_first/openapi/schemas/v3_1_1/info_schema.py
schema_first/openapi/schemas/v3_1_1/license_schema.py
schema_first/openapi/schemas/v3_1_1/media_type_object_schema.py
schema_first/openapi/schemas/v3_1_1/operation_object_schema.py
schema_first/openapi/schemas/v3_1_1/path_item_object_schema.py
schema_first/openapi/schemas/v3_1_1/reference_object_schema.py
schema_first/openapi/schemas/v3_1_1/request_body_object_schema.py
schema_first/openapi/schemas/v3_1_1/responses_object_schema.py
schema_first/openapi/schemas/v3_1_1/root_schema.py
schema_first/openapi/schemas/v3_1_1/schema_object_schema.py
schema_first/openapi/schemas/v3_1_1/server_schema.py
schema_first/openapi/schemas/v3_1_1/server_variable_object_schema.py
schema_first/specification/__init__.py
schema_first-0.6.1.dist-info/licenses/LICENSE
schema_first-0.6.1.dist-info/METADATA
schema_first-0.6.1.dist-info/WHEEL
schema_first-0.6.1.dist-info/top_level.txt
schema_first-0.6.1.dist-info/RECORD
