Metadata-Version: 2.4
Name: Schema-First
Version: 0.6.1
Summary: OpenAPI specification validator and converter to Marshmallow schemas.
Author-email: Konstantin Fadeev <fadeev@legalact.pro>
License: MIT License
Project-URL: changelog, https://github.com/flask-pro/schema-first/blob/master/CHANGES.md
Project-URL: repository, https://github.com/flask-pro/schema-first
Classifier: License :: OSI Approved :: MIT License
Classifier: Operating System :: OS Independent
Classifier: Programming Language :: Python :: 3
Requires-Python: >=3.13
License-File: LICENSE
Requires-Dist: marshmallow>=4.0.0
Requires-Dist: PyYAML>=6.0.3
Provides-Extra: dev
Requires-Dist: bandit>=1.9.2; extra == "dev"
Requires-Dist: build>=1.4.0; extra == "dev"
Requires-Dist: openapi-spec-validator>=0.5.0; extra == "dev"
Requires-Dist: pre-commit>=4.5.1; extra == "dev"
Requires-Dist: pytest>=9.0.2; extra == "dev"
Requires-Dist: pytest-cov>=7.0.0; extra == "dev"
Requires-Dist: python-dotenv>=1.2.1; extra == "dev"
Requires-Dist: twine==6.2.0; extra == "dev"
Dynamic: license-file
